plain/sessions/CHANGELOG.md
plain/sessions/README.md
plain/sessions/__init__.py
plain/sessions/admin.py
plain/sessions/chores.py
plain/sessions/config.py
plain/sessions/core.py
plain/sessions/default_settings.py
plain/sessions/exceptions.py
plain/sessions/middleware.py
plain/sessions/models.py
plain/sessions/preflight.py
plain/sessions/requests.py
plain/sessions/templates.py
plain/sessions/test.py
plain/sessions/toolbar.py
plain/sessions/views.py
plain/sessions/migrations/0001_initial.py
plain/sessions/migrations/__init__.py
plain/sessions/templates/toolbar/session.html
plain_sessions-0.42.0.dist-info/METADATA
plain_sessions-0.42.0.dist-info/WHEEL
plain_sessions-0.42.0.dist-info/licenses/LICENSE
plain_sessions-0.42.0.dist-info/RECORD
