Metadata-Version: 2.4
Name: plain.sessions
Version: 0.42.0
Summary: Database-backed sessions for managing user state across requests.
Author-email: Dave Gaeddert <dave.gaeddert@dropseed.dev>
License-Expression: BSD-3-Clause
License-File: LICENSE
Requires-Python: >=3.13
Requires-Dist: plain<1.0.0
